README.md
setup.py
global_cmd/__init__.py
global_cmd/global_cmd.py
global_cmd.egg-info/PKG-INFO
global_cmd.egg-info/SOURCES.txt
global_cmd.egg-info/dependency_links.txt
global_cmd.egg-info/entry_points.txt
global_cmd.egg-info/requires.txt
global_cmd.egg-info/top_level.txt