Metadata-Version: 2.2
Name: global_cmd
Version: 5.3
Requires-Dist: openai
Requires-Dist: pdf2image
Requires-Dist: python-dotenv
Requires-Dist: PyPDF2
Dynamic: requires-dist
